bechdelai/__init__.py
bechdelai/audio/__init__.py
bechdelai/data/__init__.py
bechdelai/data/allocine.py
bechdelai/data/bechdeltestcom.py
bechdelai/data/display.py
bechdelai/data/imdb.py
bechdelai/data/imsdb.py
bechdelai/data/opensubtitles.py
bechdelai/data/scenariotheque.py
bechdelai/data/scrap.py
bechdelai/data/src/__init__.py
bechdelai/data/src/allocine_filters.json
bechdelai/data/tests/test_display.py
bechdelai/data/tests/test_scrap.py
bechdelai/data/tests/test_tmdb_api.py
bechdelai/data/tmdb.py
bechdelai/data/wikipedia.py
bechdelai/image/__init__.py
bechdelai/image/clip.py
bechdelai/image/face_detection.py
bechdelai/image/gender_detection.py
bechdelai/image/img.py
bechdelai/image/vilt.py
bechdelai/scripts/__init__.py
bechdelai/scripts/scrap_movies.py
bechdelai/text/__init__.py
bechdelai/utils/__init__.py
bechdelai/utils/timeline.py
bechdelai/video/__init__.py
bechdelai/video/frame_extraction.py
bechdelai/video/old/__init__.py
bechdelai/video/old/face_detection.py
bechdelai/video/old/face_recognition.py
bechdelai/video/old/video_old.py
bechdelai/video/video.py
bechdelai-0.0.1a2.dist-info/entry_points.txt
bechdelai-0.0.1a2.dist-info/LICENSE
bechdelai-0.0.1a2.dist-info/WHEEL
bechdelai-0.0.1a2.dist-info/METADATA
bechdelai-0.0.1a2.dist-info/RECORD
